AutoImageExtractor/FeatureExtractor.py
AutoImageExtractor/__init__.py
AutoImageExtractor-1.1.dist-info/LICENSE
AutoImageExtractor-1.1.dist-info/METADATA
AutoImageExtractor-1.1.dist-info/WHEEL
AutoImageExtractor-1.1.dist-info/top_level.txt
AutoImageExtractor-1.1.dist-info/RECORD
