Metadata-Version: 2.1
Name: AutoImageExtractor
Version: 1.1
Summary: A python package used to automatically extract 100 different features from a group of images.
Author: Sairam Adithya
Author-email: sairamadithya2002@gmail.com
Classifier: Programming Language :: Python :: 3
Classifier: License :: OSI Approved :: MIT License
Classifier: Operating System :: OS Independent
Requires-Python: >=3.6
License-File: LICENSE
